{
  "Blue-Topaz-Codebox-Highlight@@code-line-number": false,
  "Blue-Topaz-Codebox-Highlight@@mute-code-indent-line": false,
  "Blue-Topaz-Codebox-Highlight@@code-theme-selection": "code-theme-sublime",
  "Blue-Topaz-Codebox-Highlight@@whole-code-wrap": true,
  "blue-topaz-theme@@color-scheme-options": "color-scheme-options-default",
  "blue-topaz-theme@@background-image-settings-switch": true,
  "blue-topaz-theme@@background-notebook-liked-switch": true,
  "blue-topaz-theme@@toggle-nonoverlapping-bg": true,
  "blue-topaz-theme@@toggle-bg-panel-page": false,
  "blue-topaz-theme@@background-settings-workplace-background-image": false,
  "blue-topaz-theme@@background-settings-workplace-theme-dark": "background-settings-workplace-waves2",
  "blue-topaz-theme@@background-settings-workplace-theme-light": "background-settings-workplace-waves2-light",
  "blue-topaz-theme@@font-size-code": "0.6em",
  "blue-topaz-theme@@clutter-free-headings": true,
  "blue-topaz-theme@@funny-header-anim": true,
  "blue-topaz-theme@@titlebar-close-button": "default-titlebar",
  "blue-topaz-theme@@bt-colorful-titlebar": true,
  "blue-topaz-theme@@toggle-calendar-shadow": true,
  "blue-topaz-theme@@toggle-calendar-transparent": true,
  "blue-topaz-theme@@style-options-for-calendar-plugin": "style-options-for-calendar-plugin-style-two",
  "blue-topaz-theme@@font-monospace-theme": "Consolas, 'Courier New', '霞鹜文楷 GB', 'LXGW WenKai'",
  "blue-topaz-theme@@font-size-file-header-title": "1.4em",
  "blue-topaz-theme@@table-format-options": "wrapped-table",
  "blue-topaz-theme@@brightness-4-bg": 0.9,
  "blue-topaz-theme@@background-image-settings-markdown-page-options": "background-image-settings-markdown-page-custom",
  "blue-topaz-theme@@simple-p-kanban": false,
  "blue-topaz-theme@@tag-style-option": "colorful-tag-bt",
  "blue-topaz-theme@@dark-background-file": false,
  "blue-topaz-theme@@remove-file-icons": false,
  "blue-topaz-theme@@file-name-style-option": "file-name-non-wrapped",
  "blue-topaz-theme@@file-bg-shape-option": "file-bg-rounded-rectangle",
  "blue-topaz-theme@@folder-note-underline": false,
  "blue-topaz-theme@@folder-note-dot": false,
  "blue-topaz-theme@@bt-toggle-colorful-folder": true,
  "blue-topaz-theme@@folder-style-change-options-colorful": "folder-style-change-options-colorful-border",
  "blue-topaz-theme@@text-indentation-two-em": false
}